HCTest_WechatRobot/WechatRobot.py
HCTest_WechatRobot/__init__.py
HCTest_WechatRobot-0.1.dist-info/METADATA
HCTest_WechatRobot-0.1.dist-info/WHEEL
HCTest_WechatRobot-0.1.dist-info/top_level.txt
HCTest_WechatRobot-0.1.dist-info/RECORD
